generic_qaoa/__init__.py
generic_qaoa/clause/__init__.py
generic_qaoa/clause/clause_interface.py
generic_qaoa/clause/combinatorics_clause.py
generic_qaoa/clause/mathematical_clause.py
generic_qaoa/qaoa/__init__.py
generic_qaoa/qaoa/generic_qaoa.py
generic_qaoa/qaoa/qaoa_circuit.py
generic_qaoa/utils.py
generic_qaoa/vqf_helper/__init__.py
generic_qaoa/vqf_helper/preprocessing.py
generic_qaoa-0.1.3.dist-info/WHEEL
generic_qaoa-0.1.3.dist-info/METADATA
generic_qaoa-0.1.3.dist-info/RECORD
